<annotation>
<folder></folder>
<filename>LT05_L1TP_130038_19891205_20170214_01_T2_patch_4480_2560.jpg</filename>
<path>LT05_L1TP_130038_19891205_20170214_01_T2_patch_4480_2560.jpg</path>
<source>
<database></database>
</source>
<size>
<width>640</width>
<height>640</height>
<depth>3</depth>
</size>
<segmented>0</segmented>
<object>
<name>landslides</name>
<pose>Unspecified</pose>
<truncated>0</truncated>
<difficult>0</difficult>
<occluded>0</occluded>
<bndbox><xmin>598</xmin><xmax>627</xmax><ymin>619</ymin><ymax>636</ymax></bndbox>
</object>
<object>
<name>landslides</name>
<pose>Unspecified</pose>
<truncated>0</truncated>
<difficult>0</difficult>
<occluded>0</occluded>
<bndbox><xmin>269</xmin><xmax>289</xmax><ymin>494</ymin><ymax>515</ymax></bndbox>
</object>
<object>
<name>landslides</name>
<pose>Unspecified</pose>
<truncated>0</truncated>
<difficult>0</difficult>
<occluded>0</occluded>
<bndbox><xmin>256</xmin><xmax>275</xmax><ymin>492</ymin><ymax>521</ymax></bndbox>
</object>
<object>
<name>landslides</name>
<pose>Unspecified</pose>
<truncated>0</truncated>
<difficult>0</difficult>
<occluded>0</occluded>
<bndbox><xmin>555</xmin><xmax>577</xmax><ymin>490</ymin><ymax>514</ymax></bndbox>
</object>
<object>
<name>landslides</name>
<pose>Unspecified</pose>
<truncated>0</truncated>
<difficult>0</difficult>
<occluded>0</occluded>
<bndbox><xmin>356</xmin><xmax>385</xmax><ymin>352</ymin><ymax>388</ymax></bndbox>
</object>
<object>
<name>landslides</name>
<pose>Unspecified</pose>
<truncated>0</truncated>
<difficult>0</difficult>
<occluded>0</occluded>
<bndbox><xmin>496</xmin><xmax>508</xmax><ymin>103</ymin><ymax>126</ymax></bndbox>
</object>
<object>
<name>landslides</name>
<pose>Unspecified</pose>
<truncated>0</truncated>
<difficult>0</difficult>
<occluded>0</occluded>
<bndbox><xmin>515</xmin><xmax>522</xmax><ymin>99</ymin><ymax>116</ymax></bndbox>
</object>
<object>
<name>landslides</name>
<pose>Unspecified</pose>
<truncated>0</truncated>
<difficult>0</difficult>
<occluded>0</occluded>
<bndbox><xmin>480</xmin><xmax>495</xmax><ymin>73</ymin><ymax>94</ymax></bndbox>
</object>
<object>
<name>landslides</name>
<pose>Unspecified</pose>
<truncated>0</truncated>
<difficult>0</difficult>
<occluded>0</occluded>
<bndbox><xmin>499</xmin><xmax>506</xmax><ymin>201</ymin><ymax>217</ymax></bndbox>
</object>
<object>
<name>landslides</name>
<pose>Unspecified</pose>
<truncated>0</truncated>
<difficult>0</difficult>
<occluded>0</occluded>
<bndbox><xmin>490</xmin><xmax>500</xmax><ymin>228</ymin><ymax>246</ymax></bndbox>
</object>
<object>
<name>landslides</name>
<pose>Unspecified</pose>
<truncated>0</truncated>
<difficult>0</difficult>
<occluded>0</occluded>
<bndbox><xmin>535</xmin><xmax>568</xmax><ymin>199</ymin><ymax>211</ymax></bndbox>
</object>
<object>
<name>landslides</name>
<pose>Unspecified</pose>
<truncated>0</truncated>
<difficult>0</difficult>
<occluded>0</occluded>
<bndbox><xmin>597</xmin><xmax>614</xmax><ymin>29</ymin><ymax>47</ymax></bndbox>
</object>
<object>
<name>landslides</name>
<pose>Unspecified</pose>
<truncated>0</truncated>
<difficult>0</difficult>
<occluded>0</occluded>
<bndbox><xmin>595</xmin><xmax>603</xmax><ymin>320</ymin><ymax>335</ymax></bndbox>
</object>
<object>
<name>landslides</name>
<pose>Unspecified</pose>
<truncated>0</truncated>
<difficult>0</difficult>
<occluded>0</occluded>
<bndbox><xmin>352</xmin><xmax>362</xmax><ymin>512</ymin><ymax>525</ymax></bndbox>
</object>
<object>
<name>landslides</name>
<pose>Unspecified</pose>
<truncated>0</truncated>
<difficult>0</difficult>
<occluded>0</occluded>
<bndbox><xmin>285</xmin><xmax>298</xmax><ymin>392</ymin><ymax>412</ymax></bndbox>
</object>
</annotation>